hds_stats/__init__.py
hds_stats/plot.py
hds_stats/stat.py
hds_stats-0.6.6.dist-info/licenses/LICENSE
hds_stats-0.6.6.dist-info/METADATA
hds_stats-0.6.6.dist-info/WHEEL
hds_stats-0.6.6.dist-info/top_level.txt
hds_stats-0.6.6.dist-info/RECORD
